LICENSE
pretty_jwt/__init__.py
pretty_jwt/__main__.py
pretty_jwt/_cli.py
pretty_jwt/_colorizer.py
pretty_jwt/pretty_jwt.py
pretty_jwt-0.2.0.dist-info/LICENSE
pretty_jwt-0.2.0.dist-info/WHEEL
pretty_jwt-0.2.0.dist-info/entry_points.txt
pretty_jwt-0.2.0.dist-info/METADATA
pretty_jwt-0.2.0.dist-info/RECORD
