Metadata-Version: 2.1
Name: pretty-jwt
Version: 0.2.0
Summary: Simple utility for viewing JWT tokens in console
Home-page: https://github.com/elisey/pretty_jwt
License: MIT
Author: Elisei
Author-email: elisey.rav@gmail.comp
Requires-Python: >=3.10,<4.0
Classifier: License :: OSI Approved :: MIT License
Classifier: Programming Language :: Python :: 3
Classifier: Programming Language :: Python :: 3.10
Classifier: Programming Language :: Python :: 3.11
Classifier: Programming Language :: Python :: 3
Project-URL: Repository, https://github.com/elisey/pretty_jwt
